{
	"name": "3d_basebox",
	"plugin-id": "Shape3D",
	"sid": 283522437221921,
	"isGlobal": false,
	"instanceVariables": [],
	"behaviorTypes": [],
	"effectTypes": [],
	"animations": {
		"items": [
			{
				"frames": [
					{
						"width": 120,
						"height": 120,
						"originX": 0.5,
						"originY": 0.5,
						"originalSource": "",
						"exportFormat": "lossless",
						"exportQuality": 0.8,
						"imageSpriteId": 1735692,
						"useCollisionPoly": true,
						"duration": 1
					},
					{
						"width": 120,
						"height": 120,
						"originX": 0.5,
						"originY": 0.5,
						"originalSource": "",
						"exportFormat": "lossless",
						"exportQuality": 0.8,
						"imageSpriteId": 2003058,
						"useCollisionPoly": true,
						"duration": 1
					},
					{
						"width": 120,
						"height": 120,
						"originX": 0.5,
						"originY": 0.5,
						"originalSource": "",
						"exportFormat": "lossless",
						"exportQuality": 0.8,
						"imageSpriteId": 3486355,
						"useCollisionPoly": true,
						"duration": 1
					},
					{
						"width": 120,
						"height": 120,
						"originX": 0.5,
						"originY": 0.5,
						"originalSource": "",
						"exportFormat": "lossless",
						"exportQuality": 0.8,
						"imageSpriteId": 3153922,
						"useCollisionPoly": true,
						"duration": 1
					},
					{
						"width": 120,
						"height": 120,
						"originX": 0.5,
						"originY": 0.5,
						"originalSource": "",
						"exportFormat": "lossless",
						"exportQuality": 0.8,
						"imageSpriteId": 5197551,
						"useCollisionPoly": true,
						"duration": 1
					},
					{
						"width": 120,
						"height": 120,
						"originX": 0.5,
						"originY": 0.5,
						"originalSource": "",
						"exportFormat": "lossless",
						"exportQuality": 0.8,
						"imageSpriteId": 546966,
						"useCollisionPoly": true,
						"duration": 1
					}
				],
				"sid": 777120648553959,
				"name": "Animation 1",
				"isLooping": false,
				"isPingPong": false,
				"repeatCount": 1,
				"repeatTo": 0,
				"speed": 5
			}
		],
		"subfolders": []
	}
}